_solib_k8/_U_A_A+_Urepo_Urules2+mujoco_S_S_Cmujoco_Ulib___Ulib/libmujoco.so
_solib_k8/_U_A_A+_Urepo_Urules2+mujoco_S_S_Cmujoco_Ulib___Ulib/libmujoco.so.2.2.1
envpool/__init__.py
envpool/atari/__init__.py
envpool/atari/atari_envpool.so
envpool/atari/registration.py
envpool/atari/roms/qbert.bin
envpool/atari/roms/word_zapper.bin
envpool/atari/roms/jamesbond.bin
envpool/atari/roms/earthworld.bin
envpool/atari/roms/kung_fu_master.bin
envpool/atari/roms/frogger.bin
envpool/atari/roms/asterix.bin
envpool/atari/roms/elevator_action.bin
envpool/atari/roms/name_this_game.bin
envpool/atari/roms/frostbite.bin
envpool/atari/roms/surround.bin
envpool/atari/roms/adventure.bin
envpool/atari/roms/star_gunner.bin
envpool/atari/roms/phoenix.bin
envpool/atari/roms/tutankham.bin
envpool/atari/roms/yars_revenge.bin
envpool/atari/roms/entombed.bin
envpool/atari/roms/air_raid.bin
envpool/atari/roms/pooyan.bin
envpool/atari/roms/klax.bin
envpool/atari/roms/hero.bin
envpool/atari/roms/kaboom.bin
envpool/atari/roms/riverraid.bin
envpool/atari/roms/pacman.bin
envpool/atari/roms/amidar.bin
envpool/atari/roms/venture.bin
envpool/atari/roms/demon_attack.bin
envpool/atari/roms/enduro.bin
envpool/atari/roms/time_pilot.bin
envpool/atari/roms/darkchambers.bin
envpool/atari/roms/alien.bin
envpool/atari/roms/wizard_of_wor.bin
envpool/atari/roms/othello.bin
envpool/atari/roms/space_war.bin
envpool/atari/roms/tetris.bin
envpool/atari/roms/king_kong.bin
envpool/atari/roms/flag_capture.bin
envpool/atari/roms/crazy_climber.bin
envpool/atari/roms/video_cube.bin
envpool/atari/roms/defender.bin
envpool/atari/roms/video_checkers.bin
envpool/atari/roms/turmoil.bin
envpool/atari/roms/bowling.bin
envpool/atari/roms/hangman.bin
envpool/atari/roms/keystone_kapers.bin
envpool/atari/roms/fishing_derby.bin
envpool/atari/roms/montezuma_revenge.bin
envpool/atari/roms/crossbow.bin
envpool/atari/roms/miniature_golf.bin
envpool/atari/roms/pitfall.bin
envpool/atari/roms/casino.bin
envpool/atari/roms/donkey_kong.bin
site-packages/Farama_Notifications-0.0.4.dist-info/INSTALLER
site-packages/Farama_Notifications-0.0.4.dist-info/LICENSE
site-packages/Farama_Notifications-0.0.4.dist-info/METADATA
site-packages/Farama_Notifications-0.0.4.dist-info/WHEEL
site-packages/Farama_Notifications-0.0.4.dist-info/top_level.txt
site-packages/absl_py-2.1.0.dist-info/AUTHORS
site-packages/absl_py-2.1.0.dist-info/INSTALLER
site-packages/absl_py-2.1.0.dist-info/LICENSE
site-packages/absl_py-2.1.0.dist-info/METADATA
site-packages/absl_py-2.1.0.dist-info/WHEEL
site-packages/absl_py-2.1.0.dist-info/top_level.txt
site-packages/attrs-25.1.0.dist-info/INSTALLER
site-packages/attrs-25.1.0.dist-info/METADATA
site-packages/attrs-25.1.0.dist-info/WHEEL
site-packages/attrs-25.1.0.dist-info/licenses/LICENSE
site-packages/cloudpickle-3.1.1.dist-info/INSTALLER
site-packages/cloudpickle-3.1.1.dist-info/METADATA
site-packages/cloudpickle-3.1.1.dist-info/WHEEL
site-packages/dm_env-1.6.dist-info/INSTALLER
site-packages/dm_env-1.6.dist-info/LICENSE
site-packages/dm_env-1.6.dist-info/METADATA
site-packages/dm_env-1.6.dist-info/WHEEL
site-packages/dm_env-1.6.dist-info/top_level.txt
site-packages/dm_tree-0.1.9.dist-info/INSTALLER
site-packages/dm_tree-0.1.9.dist-info/LICENSE
site-packages/dm_tree-0.1.9.dist-info/METADATA
site-packages/dm_tree-0.1.9.dist-info/WHEEL
site-packages/dm_tree-0.1.9.dist-info/top_level.txt
site-packages/gym-0.26.2.dist-info/INSTALLER
site-packages/gym-0.26.2.dist-info/LICENSE.md
site-packages/gym-0.26.2.dist-info/METADATA
site-packages/gym-0.26.2.dist-info/WHEEL
site-packages/gym-0.26.2.dist-info/top_level.txt
site-packages/gym_notices-0.0.8.dist-info/INSTALLER
site-packages/gym_notices-0.0.8.dist-info/LICENSE.txt
site-packages/gym_notices-0.0.8.dist-info/METADATA
site-packages/gym_notices-0.0.8.dist-info/WHEEL
site-packages/gym_notices-0.0.8.dist-info/top_level.txt
site-packages/gymnasium-1.1.0.dist-info/INSTALLER
site-packages/gymnasium-1.1.0.dist-info/LICENSE
site-packages/gymnasium-1.1.0.dist-info/METADATA
site-packages/gymnasium-1.1.0.dist-info/WHEEL
site-packages/gymnasium-1.1.0.dist-info/top_level.txt
site-packages/numpy-2.2.3.dist-info/INSTALLER
site-packages/numpy-2.2.3.dist-info/LICENSE.txt
site-packages/numpy-2.2.3.dist-info/METADATA
site-packages/numpy-2.2.3.dist-info/WHEEL
site-packages/numpy-2.2.3.dist-info/entry_points.txt
site-packages/optree-0.14.1.dist-info/INSTALLER
site-packages/optree-0.14.1.dist-info/LICENSE
site-packages/optree-0.14.1.dist-info/METADATA
site-packages/optree-0.14.1.dist-info/WHEEL
site-packages/optree-0.14.1.dist-info/top_level.txt
site-packages/packaging-24.2.dist-info/INSTALLER
site-packages/packaging-24.2.dist-info/LICENSE
site-packages/packaging-24.2.dist-info/LICENSE.APACHE
site-packages/packaging-24.2.dist-info/LICENSE.BSD
site-packages/packaging-24.2.dist-info/METADATA
site-packages/packaging-24.2.dist-info/WHEEL
site-packages/typing_extensions-4.12.2.dist-info/INSTALLER
site-packages/typing_extensions-4.12.2.dist-info/LICENSE
site-packages/typing_extensions-4.12.2.dist-info/METADATA
site-packages/typing_extensions-4.12.2.dist-info/WHEEL
site-packages/wrapt-1.17.2.dist-info/INSTALLER
site-packages/wrapt-1.17.2.dist-info/LICENSE
site-packages/wrapt-1.17.2.dist-info/METADATA
site-packages/wrapt-1.17.2.dist-info/WHEEL
site-packages/wrapt-1.17.2.dist-info/top_level.txt
far_envpool-0.9.0.dist-info/WHEEL
far_envpool-0.9.0.dist-info/METADATA
far_envpool-0.9.0.dist-info/RECORD
