Metadata-Version: 2.1
Name: far_envpool
Requires-Python: >=3.10,<3.13
Requires-Dist: numpy>=2.2.0
Requires-Dist: dm-env>=1.6
Requires-Dist: gym>=0.26
Requires-Dist: gymnasium>=0.26,!=0.27.0
Requires-Dist: optree>=0.6.0
Requires-Dist: jax>=0.5.0
Requires-Dist: pytest
Version: 0.9.0
